{
  "website" : {
    "style" : "fhir.layout",
    "url" : "http://smart.who.int",
    "server" : "apache",
    "org" : "WHO",
    "index-template":"index.template"
  },
  "feeds" : {
    "package" : "package-feed.xml",
    "publication" : "publication-feed.xml"
  },
  "layout-rules" : [{
     "npm" : "smart.who.int.*",
     "canonical" : "http://smart.who.int/{4}",
     "destination" : "/{4}"
   },{
     "npm" : "who.*",
     "canonical" : "http://smart.who.int/{2}",
     "destination" : "/{2}"
   },{
     "npm" : "smart.who.int.dak.*",
     "canonical" : "http://smart.who.int/dak-{5}",
     "destination" : "/dak-{5}"
    }
  ]  
}
